concloop/__init__.py
concloop/main.py
concloop-0.0.0.dist-info/LICENSE
concloop-0.0.0.dist-info/METADATA
concloop-0.0.0.dist-info/WHEEL
concloop-0.0.0.dist-info/top_level.txt
concloop-0.0.0.dist-info/RECORD
