Metadata-Version: 2.1
Name: concloop
Version: 0.0.0
Summary: An Package for running modified loops with time conditions
Home-page: UNKNOWN
Author: rootjatin (Jatin Sharma)
Author-email: <jatin100198@gmail.com>
License: UNKNOWN
Keywords: python,time based loops,loops,modified loops
Platform: UNKNOWN
Classifier: Development Status :: 1 - Planning
Classifier: Intended Audience :: Developers
Classifier: Programming Language :: Python :: 3
Classifier: Operating System :: Unix
Classifier: Operating System :: MacOS :: MacOS X
Classifier: Operating System :: Microsoft :: Windows
License-File: LICENSE
Requires-Dist: numpy
